gamgam/Center.py
gamgam/Default_Button.png
gamgam/Default_Icon.PNG
gamgam/GameObject.py
gamgam/__init__.py
gamgam-1.6.3.dist-info/METADATA
gamgam-1.6.3.dist-info/WHEEL
gamgam-1.6.3.dist-info/top_level.txt
gamgam-1.6.3.dist-info/RECORD
