Metadata-Version: 2.1
Name: gamgam
Version: 1.6.3
Summary: A game framework has many useful class and function with pygame.
Home-page: UNKNOWN
Author: Coder-Jang
Author-email: jsb060624@kakao.com
License: LGPL
Platform: UNKNOWN
Requires-Python: >=3
